{
  "id": "2014-nt1-t1-18",
  "schemaVersion": 2,
  "status": "linked",
  "lang": "de",
  "source": {
    "suite": "nebentermin1-2014",
    "year": 2014,
    "term": "nebentermin-1",
    "part": "t1",
    "nr": 18,
    "file": "[2014n1]t1-18-an.pdf"
  },
  "title": "Geschwindigkeitsfunktion",
  "rights": {
    "thirdPartyMaterial": true,
    "note": "* meaning unverified — see Aufgabenpool legend"
  },
  "assets": {
    "questionPdf": "assets/pdf/nebentermin1-2014/[2014n1]t1-18-an.pdf",
    "solutionPdf": "assets/pdf/nebentermin1-2014/lo/[2014n1]t1-18-an.pdf"
  },
  "figures": [],
  "parts": [
    {
      "id": "2014-nt1-t1-18-a",
      "label": "a",
      "format": "Offenes Antwortformat",
      "competencies": [
        {
          "code": "AN 4.3",
          "description": "das bestimmte Integral in verschiedenen Kontexten deuten und entsprechende Sachverhalte durch Integrale beschreiben können",
          "source": "aufgabenpool",
          "verifiedAt": "2026-06-30"
        }
      ],
      "externalRefs": [
        {
          "system": "aufgabenpool",
          "id": "1_356a",
          "baseId": "1_356",
          "url": "https://www.aufgabenpool.at/amn/Typ-1/67/Geschwindigkeitsfunktion.pdf",
          "license": "CC-BY-4.0",
          "verifiedAt": "2026-06-30"
        }
      ],
      "figures": [],
      "solution": []
    }
  ],
  "externalRefs": [
    {
      "system": "aufgabenpool",
      "id": "1_356",
      "baseId": "1_356",
      "url": "https://www.aufgabenpool.at/amn/Typ-1/67/Geschwindigkeitsfunktion.pdf",
      "license": "CC-BY-4.0",
      "verifiedAt": "2026-06-30"
    }
  ]
}