{
  "id": "2015-nt1-t1-14",
  "schemaVersion": 2,
  "status": "linked",
  "lang": "de",
  "source": {
    "suite": "nebentermin1-2015",
    "year": 2015,
    "term": "nebentermin-1",
    "part": "t1",
    "nr": 14,
    "file": "[2015n1]t1-14-an.pdf"
  },
  "title": "Ableitung einer Winkelfunktion",
  "rights": {
    "thirdPartyMaterial": true,
    "note": "* meaning unverified — see Aufgabenpool legend"
  },
  "assets": {
    "questionPdf": "assets/pdf/nebentermin1-2015/[2015n1]t1-14-an.pdf",
    "solutionPdf": "assets/pdf/nebentermin1-2015/lo/[2015n1]t1-14-an.pdf"
  },
  "figures": [],
  "parts": [
    {
      "id": "2015-nt1-t1-14-a",
      "label": "a",
      "format": "Offenes Antwortformat",
      "competencies": [
        {
          "code": "AN 2.1",
          "description": "einfache Regeln des Differenzierens kennen und anwenden können: Potenzregel, Summenregel, Regeln für [k * f(x)]' und [f(k *x)]' (vgl. Inhaltsbereich Funktionale Abhängigkeiten)",
          "source": "aufgabenpool",
          "verifiedAt": "2026-06-30"
        }
      ],
      "externalRefs": [
        {
          "system": "aufgabenpool",
          "id": "1_432a",
          "baseId": "1_432",
          "url": "https://www.aufgabenpool.at/amn/Typ-1/140/Ableitung%20einer%20Winkelfunktion.pdf",
          "license": "CC-BY-4.0",
          "verifiedAt": "2026-06-30"
        }
      ],
      "figures": [],
      "solution": []
    }
  ],
  "externalRefs": [
    {
      "system": "aufgabenpool",
      "id": "1_432",
      "baseId": "1_432",
      "url": "https://www.aufgabenpool.at/amn/Typ-1/140/Ableitung%20einer%20Winkelfunktion.pdf",
      "license": "CC-BY-4.0",
      "verifiedAt": "2026-06-30"
    }
  ]
}