{
  "id": "2018-nt2-t1-03",
  "schemaVersion": 2,
  "status": "linked",
  "lang": "de",
  "source": {
    "suite": "nebentermin2-2018",
    "year": 2018,
    "term": "nebentermin-2",
    "part": "t1",
    "nr": 3,
    "file": "[2018n2]t1-3-fa.pdf"
  },
  "title": "Lösungen einer quadratischen Gleichung",
  "rights": {
    "thirdPartyMaterial": true,
    "note": "* meaning unverified — see Aufgabenpool legend"
  },
  "assets": {
    "questionPdf": "assets/pdf/nebentermin2-2018/[2018n2]t1-3-fa.pdf",
    "solutionPdf": "assets/pdf/nebentermin2-2018/lo/[2018n2]t1-3-fa.pdf"
  },
  "figures": [],
  "parts": [
    {
      "id": "2018-nt2-t1-03-a",
      "label": "a",
      "format": "Lückentext",
      "competencies": [
        {
          "code": "AG 2.3",
          "description": "quadratische Gleichungen in einer Variablen umformen/lösen, über Lösungsfälle Bescheid wissen, Lösungen und Lösungsfälle (auch geometrisch) deuten können",
          "source": "aufgabenpool",
          "verifiedAt": "2026-06-30"
        }
      ],
      "externalRefs": [
        {
          "system": "aufgabenpool",
          "id": "1_592a",
          "baseId": "1_592",
          "url": "https://www.aufgabenpool.at/amn/Typ-1/301/L%C3%B6sungen%20einer%20quadratischen%20Gleichung.pdf",
          "license": "CC-BY-4.0",
          "verifiedAt": "2026-06-30"
        }
      ],
      "figures": [],
      "solution": []
    }
  ],
  "externalRefs": [
    {
      "system": "aufgabenpool",
      "id": "1_592",
      "baseId": "1_592",
      "url": "https://www.aufgabenpool.at/amn/Typ-1/301/L%C3%B6sungen%20einer%20quadratischen%20Gleichung.pdf",
      "license": "CC-BY-4.0",
      "verifiedAt": "2026-06-30"
    }
  ]
}